damn/__init__.py
damn/calculator.py
damn/compose.py
damn/definition/__init__.py
damn/definition/abc.py
damn/definition/domain.py
damn/definition/in_pair.py
damn/definition/in_single.py
damn/error.py
damn/lib/__init__.py
damn/lib/wolfram.py
damn/utils.py
damn/value/__init__.py
damn/value/abc.py
damn/value/decimal.py
damn/value/rational.py
damnlang-0.1.1.dist-info/WHEEL
damnlang-0.1.1.dist-info/METADATA
damnlang-0.1.1.dist-info/RECORD
