Metadata-Version: 2.1
Name: damnlang
Version: 0.1.1
Summary: Damn
License: MIT
Author: timoniq
Requires-Python: >=3.9,<4.0
Classifier: License :: OSI Approved :: MIT License
Classifier: Programming Language :: Python :: 3
Classifier: Programming Language :: Python :: 3.9
Classifier: Programming Language :: Python :: 3.10
Requires-Dist: aiohttp (>=3.8.3,<4.0.0)
